LICENSE.md
poetry_plugin_upgrade/__init__.py
poetry_plugin_upgrade/command.py
poetry_plugin_upgrade/plugin.py
poetry_plugin_upgrade-0.3.0.dist-info/LICENSE.md
poetry_plugin_upgrade-0.3.0.dist-info/METADATA
poetry_plugin_upgrade-0.3.0.dist-info/WHEEL
poetry_plugin_upgrade-0.3.0.dist-info/entry_points.txt
poetry_plugin_upgrade-0.3.0.dist-info/RECORD
