Metadata-Version: 2.1
Name: poetry-plugin-upgrade
Version: 0.3.0
Summary: Poetry plugin that updates dependencies and bumps their versions in pyproject.toml file
Home-page: https://github.com/apoclyps/poetry-plugin-upgrade
License: MIT
Keywords: packaging,dependency,poetry,update,upgrade
Author: Kyle Harrison
Author-email: kyle.harrison.dev@gmail.com
Requires-Python: >=3.10,<4.0
Classifier: Development Status :: 5 - Production/Stable
Classifier: License :: OSI Approved :: MIT License
Classifier: Operating System :: OS Independent
Classifier: Programming Language :: Python :: 3
Classifier: Programming Language :: Python :: 3.10
Classifier: Programming Language :: Python :: 3.11
Requires-Dist: poetry (>=1.8.3,<3.0.0)
Project-URL: Repository, https://github.com/apoclyps/poetry-plugin-upgrade
